Ofpp/__init__.py
Ofpp/field_parser.py
Ofpp/mesh_parser.py
Ofpp/utils.py
Ofpp-0.12.dist-info/LICENSE
Ofpp-0.12.dist-info/METADATA
Ofpp-0.12.dist-info/WHEEL
Ofpp-0.12.dist-info/top_level.txt
Ofpp-0.12.dist-info/RECORD
